lute/LICENSE.txt
lute/__init__.py
lute/app_factory.py
lute/main.py
lute/ankiexport/__init__.py
lute/ankiexport/criteria.py
lute/ankiexport/exceptions.py
lute/ankiexport/field_mapping.py
lute/ankiexport/forms.py
lute/ankiexport/routes.py
lute/ankiexport/service.py
lute/backup/__init__.py
lute/backup/routes.py
lute/backup/service.py
lute/bing/__init__.py
lute/bing/routes.py
lute/book/__init__.py
lute/book/datatables.py
lute/book/forms.py
lute/book/model.py
lute/book/routes.py
lute/book/service.py
lute/book/stats.py
lute/bookmarks/__init__.py
lute/bookmarks/datatables.py
lute/bookmarks/routes.py
lute/cli/README.md
lute/cli/__init__.py
lute/cli/commands.py
lute/cli/import_books.py
lute/cli/language_term_export.py
lute/config/__init__.py
lute/config/app_config.py
lute/config/config.yml.docker
lute/config/config.yml.example
lute/config/config.yml.prod
lute/db/__init__.py
lute/db/data_cleanup.py
lute/db/demo.py
lute/db/management.py
lute/db/language_defs/README.md
lute/db/language_defs/generate_dict_markdown_table.py
lute/db/language_defs/generate_language_listing.py
lute/db/language_defs/requirements.txt
lute/db/language_defs/verify_files.py
lute/db/language_defs/.github/workflows/ci.yml
lute/db/language_defs/_templates/definition.yaml.example
lute/db/language_defs/_templates/story.txt.example
lute/db/language_defs/afrikaans/definition.yaml
lute/db/language_defs/afrikaans/die_diere_grawe_n_put.txt
lute/db/language_defs/ainu/definition.yaml
lute/db/language_defs/ainu/story_1.txt
lute/db/language_defs/albanian/definition.yaml
lute/db/language_defs/albanian/shqiponja_dhe_mbreti.txt
lute/db/language_defs/amharic/definition.yaml
lute/db/language_defs/amharic/story_1.txt
lute/db/language_defs/arabic/ar_demo.txt
lute/db/language_defs/arabic/definition.yaml
lute/db/language_defs/armenian/definition.yaml
lute/db/language_defs/armenian/story_1.txt
lute/db/language_defs/azerbaijani/definition.yaml
lute/db/language_defs/azerbaijani/story_1.txt
lute3-3.10.1.dist-info/entry_points.txt
lute3-3.10.1.dist-info/LICENSE.txt
lute3-3.10.1.dist-info/WHEEL
lute3-3.10.1.dist-info/METADATA
lute3-3.10.1.dist-info/RECORD
