Metadata-Version: 2.3
Name: lute3
Version: 3.10.1
Summary: Learning Using Texts
Author-email: Jeff Zohrab <jzohrab@gmail.com>
Requires-Python: >=3.8
Requires-Dist: Flask-SQLAlchemy>=3.1.1,<4
Requires-Dist: Flask-WTF>=1.2.1,<2
Requires-Dist: natto-py>=1.0.1,<2
Requires-Dist: jaconv>=0.3.4,<1
Requires-Dist: platformdirs>=3.10.0,<4
Requires-Dist: requests>=2.31.0,<3
Requires-Dist: beautifulsoup4>=4.12.2,<5
Requires-Dist: PyYAML>=6.0.1,<7
Requires-Dist: toml>=0.10.2,<1
Requires-Dist: waitress>=2.1.2,<3
Requires-Dist: openepub>=0.0.8,<1
Requires-Dist: pyparsing>=3.1.4
Requires-Dist: pypdf>=3.17.4
Requires-Dist: subtitle-parser>=1.3.0
Requires-Dist: ahocorapy>=1.6.2
Requires-Dist: coverage>=7.3.1,<8 ; extra == "dev"
Requires-Dist: invoke>=2.2.0,<3 ; extra == "dev"
Requires-Dist: pip>=23.0.1 ; extra == "dev"
Requires-Dist: pipdeptree>=2.13.0,<3 ; extra == "dev"
Requires-Dist: pylint>=2.17.5,<4 ; extra == "dev"
Requires-Dist: pytest-bdd>=7.0.0,<8 ; extra == "dev"
Requires-Dist: pytest-splinter>=3.3.2,<4 ; extra == "dev"
Requires-Dist: playwright>=1.39.0,<2 ; extra == "dev"
Requires-Dist: pre-commit>=3.5.0,<4 ; extra == "dev"
Requires-Dist: black>=23.10.1,<24 ; extra == "dev"
Project-URL: Home, https://github.com/luteorg/lute-v3
Provides-Extra: dev
